MANIFEST.in
README.md
pyproject.toml
setup.py
amuse_capreole.egg-info/PKG-INFO
amuse_capreole.egg-info/SOURCES.txt
amuse_capreole.egg-info/dependency_links.txt
amuse_capreole.egg-info/requires.txt
amuse_capreole.egg-info/top_level.txt
src/amuse/community/capreole/Makefile
src/amuse/community/capreole/__init__.py
src/amuse/community/capreole/_version.py
src/amuse/community/capreole/interface.F90
src/amuse/community/capreole/interface.py
src/amuse/community/capreole/readme.txt
src/amuse/community/capreole/src/Doxyfile
src/amuse/community/capreole/src/Makefile
src/amuse/community/capreole/src/abundances.f90
src/amuse/community/capreole/src/ah3out.F90
src/amuse/community/capreole/src/amuse_atomic.f90
src/amuse/community/capreole/src/amuse_cart-coords.F90
src/amuse/community/capreole/src/amuse_helpers.F90
src/amuse/community/capreole/src/amuse_mesh.F90
src/amuse/community/capreole/src/amuse_mpi.F90
src/amuse/community/capreole/src/amuse_problem.F90
src/amuse/community/capreole/src/atomic.f90
src/amuse/community/capreole/src/boundary.F90
src/amuse/community/capreole/src/capreole.F90
src/amuse/community/capreole/src/cart-amuse.F90
src/amuse/community/capreole/src/cart-coords.F90
src/amuse/community/capreole/src/cart-routines.f90
src/amuse/community/capreole/src/cgsastroconstants.f90
src/amuse/community/capreole/src/cgsconstants.f90
src/amuse/community/capreole/src/cgsphotoconstants.f90
src/amuse/community/capreole/src/clocks.f90
src/amuse/community/capreole/src/evolve.F90
src/amuse/community/capreole/src/file_admin.f90
src/amuse/community/capreole/src/fthread.f
src/amuse/community/capreole/src/glcapreole.F90
src/amuse/community/capreole/src/hydro.F90
src/amuse/community/capreole/src/integrate-strang.F90
src/amuse/community/capreole/src/lof-2.2.f90
src/amuse/community/capreole/src/mathconstants.f90
src/amuse/community/capreole/src/mesh.F90
src/amuse/community/capreole/src/mpi.F90
src/amuse/community/capreole/src/no_ionic.f90
src/amuse/community/capreole/src/no_mpi.F90
src/amuse/community/capreole/src/noscaling.f90
src/amuse/community/capreole/src/precision.f90
src/amuse/community/capreole/src/protection2.F90
src/amuse/community/capreole/src/pt.c
